install_freedesktop.py
install_freedesktop-0.1.2.dist-info/entry_points.txt
install_freedesktop-0.1.2.dist-info/RECORD
install_freedesktop-0.1.2.dist-info/WHEEL
install_freedesktop-0.1.2.dist-info/METADATA
install_freedesktop-0.1.2.dist-info/top_level.txt
install_freedesktop-0.1.2.dist-info/metadata.json
install_freedesktop-0.1.2.dist-info/DESCRIPTION.rst
