Metadata-Version: 2.0
Name: install-freedesktop
Version: 0.1.2
Summary: Setuptools extension to install freedesktop.org app icons
Home-page: https://github.com/welshjf/install_freedesktop
Author: Jacob Welsh
Author-email: jacob@welshcomputing.com
License: Apache License 2.0
Platform: UNKNOWN
Classifier: Development Status :: 3 - Alpha
Classifier: Intended Audience :: Developers
Classifier: License :: OSI Approved :: Apache Software License
Classifier: Operating System :: POSIX
Classifier: Programming Language :: Python
Classifier: Programming Language :: Python :: 2.6
Classifier: Programming Language :: Python :: 2.7
Classifier: Programming Language :: Python :: 3
Classifier: Topic :: Desktop Environment
Classifier: Topic :: Software Development :: Build Tools
Requires-Dist: setuptools
